jaikirantestingpip/__init__.py
jaikirantestingpip/test1.py
jaikirantestingpip-0.0.1.dist-info/LICENSE
jaikirantestingpip-0.0.1.dist-info/METADATA
jaikirantestingpip-0.0.1.dist-info/WHEEL
jaikirantestingpip-0.0.1.dist-info/top_level.txt
jaikirantestingpip-0.0.1.dist-info/RECORD
