Metadata-Version: 2.1
Name: jaikirantestingpip
Version: 0.0.1
Summary: For testing py packaging
Home-page: https://github.com/jaikirankn/test1.git
Author: jaikiran K
Author-email: jaikiran123@gmail.com
License: UNKNOWN
Platform: UNKNOWN
Classifier: Programming Language :: Python :: 3
Classifier: License :: OSI Approved :: MIT License
Classifier: Operating System :: OS Independent
Requires-Python: >=3.7
License-File: LICENSE
